ash/__init__.py
ash/binding.py
ash/canonicalize.py
ash/compare.py
ash/core.py
ash/proof.py
ash/client/__init__.py
ash/client/client.py
ash/config/__init__.py
ash/config/scope_policies.py
ash/core/__init__.py
ash/core/canonicalize.py
ash/core/compare.py
ash/core/errors.py
ash/core/proof.py
ash/core/types.py
ash/middleware/__init__.py
ash/middleware/django.py
ash/middleware/fastapi.py
ash/middleware/flask.py
ash/server/__init__.py
ash/server/context.py
ash/server/types.py
ash/server/verify.py
ash/server/middleware/__init__.py
ash/server/middleware/flask.py
ash/server/stores/__init__.py
ash/server/stores/memory.py
ash/server/stores/redis.py
ash/stores/__init__.py
ash/stores/base.py
ash/stores/memory.py
ash/stores/redis.py
ash_sdk-2.3.3.dist-info/METADATA
ash_sdk-2.3.3.dist-info/WHEEL
ash_sdk-2.3.3.dist-info/RECORD
