Metadata-Version: 2.4
Name: ash-sdk
Version: 2.3.3
Summary: ASH (Application Security Hash) - RFC 8785 compliant request integrity verification with server-signed seals, anti-replay protection, and zero client secrets
Project-URL: Homepage, https://github.com/3maem/ash
Project-URL: Repository, https://github.com/3maem/ash
Project-URL: Documentation, https://github.com/3maem/ash#readme
Author: 3maem
License: Proprietary
Keywords: anti-replay,flask,integrity,security,verification
Classifier: Development Status :: 5 - Production/Stable
Classifier: Framework :: Flask
Classifier: Intended Audience :: Developers
Classifier: License :: Other/Proprietary License
Classifier: Programming Language :: Python :: 3
Classifier: Programming Language :: Python :: 3.10
Classifier: Programming Language :: Python :: 3.11
Classifier: Programming Language :: Python :: 3.12
Classifier: Topic :: Security
Classifier: Typing :: Typed
Requires-Python: >=3.10
Provides-Extra: all
Requires-Dist: flask>=2.0.0; extra == 'all'
Requires-Dist: redis>=4.0.0; extra == 'all'
Provides-Extra: dev
Requires-Dist: flask>=2.0.0; extra == 'dev'
Requires-Dist: mypy>=1.0.0; extra == 'dev'
Requires-Dist: pytest-asyncio>=0.21.0; extra == 'dev'
Requires-Dist: pytest>=7.0.0; extra == 'dev'
Requires-Dist: redis>=4.0.0; extra == 'dev'
Requires-Dist: ruff>=0.1.0; extra == 'dev'
Provides-Extra: flask
Requires-Dist: flask>=2.0.0; extra == 'flask'
Provides-Extra: redis
Requires-Dist: redis>=4.0.0; extra == 'redis'
